stpip
