Metadata-Version: 1.2
Name: stpip
Version: 19.3.5
Summary: a pepy.tech webscraping for pypi download statistics
Home-page: https://github.com/astrom-tom/stpip
Author: Romain Thomas
License: GNU GPL v3
Platform: UNKNOWN
Requires-Python: >=3.5
